wmgr/__init__.py
wmgr/common.py
wmgr/gethexid.py
wmgr/getpid.py
wmgr/getwid.py
wmgr/getwindowname.py
wmgr/winactivate.py
wmgr/winactivate.py.lprof
wmgr/winmove.py
wmgr/winutil.sh
wmgr-0.1.0.dist-info/METADATA
wmgr-0.1.0.dist-info/WHEEL
wmgr-0.1.0.dist-info/top_level.txt
wmgr-0.1.0.dist-info/RECORD
